itask/configs.py
itask/console.py
itask/dataprovider.py
itask/default_keys.yaml
itask/imenu.py
itask/itask.py
itask/selection.py
itask/taskwarriorreportparser.py
itask/taskwarriorwrapper.py
itask/terminal_resize_listener.py
itask/viewer.py
iTask-0.3.11.dist-info/LICENSE
iTask-0.3.11.dist-info/METADATA
iTask-0.3.11.dist-info/WHEEL
iTask-0.3.11.dist-info/entry_points.txt
iTask-0.3.11.dist-info/top_level.txt
iTask-0.3.11.dist-info/RECORD
